zrandomlist/__init__.py
zrandomlist-0.3.dist-info/METADATA
zrandomlist-0.3.dist-info/WHEEL
zrandomlist-0.3.dist-info/top_level.txt
zrandomlist-0.3.dist-info/RECORD
